cfn_ami_to_mapping/__init__.py
cfn_ami_to_mapping/_version.py
cfn_ami_to_mapping/run.py
cfn_ami_to_mapping/enrich/__init__.py
cfn_ami_to_mapping/enrich/enrich.py
cfn_ami_to_mapping/generate/__init__.py
cfn_ami_to_mapping/generate/generate.py
cfn_ami_to_mapping/get/__init__.py
cfn_ami_to_mapping/get/get.py
cfn_ami_to_mapping/transform/__init__.py
cfn_ami_to_mapping/transform/transform.py
cfn_ami_to_mapping/validate/__init__.py
cfn_ami_to_mapping/validate/validate.py
cfn_ami_to_mapping-0.8.3.dist-info/LICENSE
cfn_ami_to_mapping-0.8.3.dist-info/METADATA
cfn_ami_to_mapping-0.8.3.dist-info/WHEEL
cfn_ami_to_mapping-0.8.3.dist-info/entry_points.txt
cfn_ami_to_mapping-0.8.3.dist-info/top_level.txt
cfn_ami_to_mapping-0.8.3.dist-info/RECORD
