Metadata-Version: 2.1
Name: cfn-ami-to-mapping
Version: 0.8.3
Summary: Get AMI IDs per region automatically for your CloudFormation template
Home-page: https://github.com/99stealth/cfn-ami-to-mapping
Author: Roman Banakh
Author-email: banakh.ri@gmail.com
License: MIT
Platform: UNKNOWN
Classifier: License :: OSI Approved :: MIT License
Classifier: Programming Language :: Python :: 2
Classifier: Programming Language :: Python :: 2.7
Classifier: Programming Language :: Python :: 3
Classifier: Programming Language :: Python :: 3.5
Classifier: Programming Language :: Python :: 3.6
Classifier: Programming Language :: Python :: 3.7
Classifier: Programming Language :: Python :: 3.8
Requires-Dist: argparse
Requires-Dist: boto3
Requires-Dist: pyjson
Requires-Dist: pyyaml
Requires-Dist: more-itertools
Requires-Dist: futures
